08_Johnson_Counter/johnson_counter.v
module johnson_counter(
    input clk,
    input reset,
    output reg [3:0] q
);

always @(posedge clk or posedge reset)
begin
    if (reset)
        q <= 4'b0000;
    else
        q <= {~q[0], q[3:1]};
end

endmodule

08_Johnson_Counter/tb_johnson_counter.v
`timescale 1ns/1ps

module tb_johnson_counter;

reg clk;
reg reset;
wire [3:0] q;

// Instantiate the Johnson Counter
johnson_counter uut (
    .clk(clk),
    .reset(reset),
    .q(q)
);

// Clock Generation
always #5 clk = ~clk;

initial begin
    $dumpfile("johnson_counter.vcd");
    $dumpvars(0, tb_johnson_counter);

    $display("Time\tReset\tQ");
    $monitor("%0t\t%b\t%b", $time, reset, q);

    clk = 0;
    reset = 1;

    #10 reset = 0;

    #80;

    $finish;
end

endmodule

08_Johnson_Counter/johnson_counter.vcd
$date
	Fri Jul 10 16:11:55 2026
$end
$version
	Icarus Verilog
$end
$timescale
	1ps
$end
$scope module tb_johnson_counter $end
$var wire 4 ! q [3:0] $end
$var reg 1 " clk $end
$var reg 1 # reset $end
$scope module uut $end
$var wire 1 " clk $end
$var wire 1 # reset $end
$var reg 4 $ q [3:0] $end
$upscope $end
$upscope $end
$enddefinitions $end
$comment Show the parameter values. $end
$dumpall
$end
#0
$dumpvars
b0 $
1#
0"
b0 !
$end
#5000
1"
#10000
0"
0#
#15000
b1000 !
b1000 $
1"
#20000
0"
#25000
b1100 !
b1100 $
1"
#30000
0"
#35000
b1110 !
b1110 $
1"
#40000
0"
#45000
b1111 !
b1111 $
1"
#50000
0"
#55000
b111 !
b111 $
1"
#60000
0"
#65000
b11 !
b11 $
1"
#70000
0"
#75000
b1 !
b1 $
1"
#80000
0"
#85000
b0 !
b0 $
1"
