12_UART_Transmitter/uart_tx.v
module uart_tx(
    input clk,
    input reset,
    input start,
    input [7:0] data_in,
    output reg tx,
    output reg busy
);

reg [3:0] bit_count;
reg [9:0] shift_reg;

always @(posedge clk or posedge reset)
begin
    if(reset)
    begin
        tx <= 1'b1;
        busy <= 0;
        bit_count <= 0;
        shift_reg <= 10'b1111111111;
    end
    else
    begin
        if(start && !busy)
        begin
            busy <= 1;
            shift_reg <= {1'b1, data_in, 1'b0}; // Stop + Data + Start
            bit_count <= 0;
        end
        else if(busy)
        begin
            tx <= shift_reg[0];
            shift_reg <= {1'b1, shift_reg[9:1]};
            bit_count <= bit_count + 1;

            if(bit_count == 9)
            begin
                busy <= 0;
                tx <= 1'b1;
            end
        end
    end
end

endmodule

12_UART_Transmitter/tb_uart_tx.v
`timescale 1ns/1ps

module tb_uart_tx;

reg clk;
reg reset;
reg start;
reg [7:0] data_in;

wire tx;
wire busy;

uart_tx uut (
    .clk(clk),
    .reset(reset),
    .start(start),
    .data_in(data_in),
    .tx(tx),
    .busy(busy)
);

// Clock Generation
always #5 clk = ~clk;

initial
begin
    $dumpfile("uart_tx.vcd");
    $dumpvars(0, tb_uart_tx);

    clk = 0;
    reset = 1;
    start = 0;
    data_in = 8'b10101010;

    #10 reset = 0;

    #10 start = 1;
    #10 start = 0;

    #200;

    $finish;
end

initial
begin
    $display("Time\tStart\tBusy\tTX");
    $monitor("%0t\t%b\t%b\t%b",$time,start,busy,tx);
end

endmodule

12_UART_Transmitter/uart_tx.vcd
$date
	Sat Jul 11 16:11:20 2026
$end
$version
	Icarus Verilog
$end
$timescale
	1ps
$end
$scope module tb_uart_tx $end
$var wire 1 ! tx $end
$var wire 1 " busy $end
$var reg 1 # clk $end
$var reg 8 $ data_in [7:0] $end
$var reg 1 % reset $end
$var reg 1 & start $end
$scope module uut $end
$var wire 1 # clk $end
$var wire 8 ' data_in [7:0] $end
$var wire 1 % reset $end
$var wire 1 & start $end
$var reg 4 ( bit_count [3:0] $end
$var reg 1 " busy $end
$var reg 10 ) shift_reg [9:0] $end
$var reg 1 ! tx $end
$upscope $end
$upscope $end
$enddefinitions $end
$comment Show the parameter values. $end
$dumpall
$end
#0
$dumpvars
b1111111111 )
b0 (
b10101010 '
0&
1%
b10101010 $
0#
0"
1!
$end
#5000
1#
#10000
0#
0%
#15000
1#
#20000
0#
1&
#25000
b1101010100 )
1"
1#
#30000
0#
0&
#35000
b1 (
b1110101010 )
0!
1#
#40000
0#
#45000
b10 (
b1111010101 )
1#
#50000
0#
#55000
b11 (
b1111101010 )
1!
1#
#60000
0#
#65000
b100 (
b1111110101 )
0!
1#
#70000
0#
#75000
b101 (
b1111111010 )
1!
1#
#80000
0#
#85000
b110 (
b1111111101 )
0!
1#
#90000
0#
#95000
b111 (
b1111111110 )
1!
1#
#100000
0#
#105000
b1000 (
b1111111111 )
0!
1#
#110000
0#
#115000
b1001 (
1!
1#
#120000
0#
#125000
0"
b1010 (
1#
