04_Shift_Register/shift_register.v
module shift_register(
    input clk,
    input reset,
    input serial_in,
    output serial_out
);

reg [3:0] shift_reg;

always @(posedge clk or posedge reset)
begin
    if (reset)
        shift_reg <= 4'b0000;
    else
        shift_reg <= {shift_reg[2:0], serial_in};
end

assign serial_out = shift_reg[3];

endmodule

04_Shift_Register/tb_shift_register.v
`timescale 1ns/1ps

module tb_shift_register;

reg clk;
reg reset;
reg serial_in;
wire serial_out;

shift_register uut (
    .clk(clk),
    .reset(reset),
    .serial_in(serial_in),
    .serial_out(serial_out)
);

// Clock generation
always #5 clk = ~clk;

initial begin
    $dumpfile("shift.vcd");
    $dumpvars(0, tb_shift_register);

    $display("Time\tReset\tSerial_in\tSerial_out");
    $monitor("%0t\t%b\t%b\t\t%b",
             $time, reset, serial_in, serial_out);

    clk = 0;
    reset = 1;
    serial_in = 0;

    #10;
    reset = 0;

    serial_in = 1; #10;
    serial_in = 0; #10;
    serial_in = 1; #10;
    serial_in = 1; #10;
    serial_in = 0; #10;


    #10;
    $finish;
end

endmodule

04_Shift_Register/shift.vcd
$date
	Thu Jul  9 14:58:02 2026
$end
$version
	Icarus Verilog
$end
$timescale
	1ps
$end
$scope module tb_shift_register $end
$var wire 1 ! serial_out $end
$var reg 1 " clk $end
$var reg 1 # reset $end
$var reg 1 $ serial_in $end
$scope module uut $end
$var wire 1 " clk $end
$var wire 1 # reset $end
$var wire 1 $ serial_in $end
$var wire 1 ! serial_out $end
$var reg 4 % shift_reg [3:0] $end
$upscope $end
$upscope $end
$enddefinitions $end
$comment Show the parameter values. $end
$dumpall
$end
#0
$dumpvars
b0 %
0$
1#
0"
0!
$end
#5000
1"
#10000
0"
1$
0#
#15000
b1 %
1"
#20000
0"
0$
#25000
b10 %
1"
#30000
0"
1$
#35000
b101 %
1"
#40000
0"
#45000
1!
b1011 %
1"
#50000
0"
0$
#55000
0!
b110 %
1"
#60000
0"
#65000
1!
b1100 %
1"
