11_Sequence_Detector/11_sequence_detector.v
module sequence_detector(
    input clk,
    input reset,
    input din,
    output reg detected
);

parameter S0 = 3'b000,
          S1 = 3'b001,
          S2 = 3'b010,
          S3 = 3'b011,
          S4 = 3'b100;

reg [2:0] state;

always @(posedge clk or posedge reset)
begin
    if (reset)
    begin
        state <= S0;
        detected <= 0;
    end
    else
    begin
        case(state)

        S0:
        begin
            detected <= 0;
            if(din)
                state <= S1;
            else
                state <= S0;
        end

        S1:
        begin
            detected <= 0;
            if(din)
                state <= S1;
            else
                state <= S2;
        end

        S2:
        begin
            detected <= 0;
            if(din)
                state <= S3;
            else
                state <= S0;
        end

        S3:
        begin
            detected <= 0;
            if(din)
                state <= S4;
            else
                state <= S2;
        end

        S4:
        begin
            detected <= 1;
            if(din)
                state <= S1;
            else
                state <= S2;
        end

        default:
        begin
            state <= S0;
            detected <= 0;
        end

        endcase
    end
end

endmodule

11_Sequence_Detector/tb_11_sequence_detector.v
`timescale 1ns/1ps

module tb_sequence_detector;

reg clk;
reg reset;
reg din;
wire detected;

sequence_detector uut (
    .clk(clk),
    .reset(reset),
    .din(din),
    .detected(detected)
);

// Clock Generation
always #5 clk = ~clk;

initial
begin
    $dumpfile("sequence_detector.vcd");
    $dumpvars(0, tb_sequence_detector);

    clk = 0;
    reset = 1;
    din = 0;

    #10 reset = 0;

    // Input Sequence: 1 0 1 1 (Detected)
    #10 din = 1;
    #10 din = 0;
    #10 din = 1;
    #10 din = 1;

    // Random Bits
    #10 din = 0;
    #10 din = 1;
    #10 din = 1;
    #10 din = 0;

    // Again: 1 0 1 1
    #10 din = 1;
    #10 din = 0;
    #10 din = 1;
    #10 din = 1;

    #20;

    $finish;
end

initial
begin
    $display("Time\tReset\tDIN\tDetected");
    $monitor("%0t\t%b\t%b\t%b",$time,reset,din,detected);
end

endmodule

11_Sequence_Detector/sequence_detector.vcd
$date
	Sat Jul 11 15:59:05 2026
$end
$version
	Icarus Verilog
$end
$timescale
	1ps
$end
$scope module tb_sequence_detector $end
$var wire 1 ! detected $end
$var reg 1 " clk $end
$var reg 1 # din $end
$var reg 1 $ reset $end
$scope module uut $end
$var wire 1 " clk $end
$var wire 1 # din $end
$var wire 1 $ reset $end
$var parameter 3 % S0 $end
$var parameter 3 & S1 $end
$var parameter 3 ' S2 $end
$var parameter 3 ( S3 $end
$var parameter 3 ) S4 $end
$var reg 1 ! detected $end
$var reg 3 * state [2:0] $end
$upscope $end
$upscope $end
$enddefinitions $end
$comment Show the parameter values. $end
$dumpall
b100 )
b11 (
b10 '
b1 &
b0 %
$end
#0
$dumpvars
b0 *
1$
0#
0"
0!
$end
#5000
1"
#10000
0"
0$
#15000
1"
#20000
0"
1#
#25000
b1 *
1"
#30000
0"
0#
#35000
b10 *
1"
#40000
0"
1#
#45000
b11 *
1"
#50000
0"
#55000
b100 *
1"
#60000
0"
0#
#65000
b10 *
1!
1"
#70000
0"
1#
#75000
b11 *
0!
1"
#80000
0"
#85000
b100 *
1"
#90000
0"
0#
#95000
b10 *
1!
1"
#100000
0"
1#
#105000
b11 *
0!
1"
#110000
0"
0#
#115000
b10 *
1"
#120000
0"
1#
#125000
b11 *
1"
#130000
0"
#135000
b100 *
1"
#140000
0"
#145000
b1 *
1!
1"
