06_Up_Down_Counter/up_down_counter.v
module up_down_counter(
    input clk,
    input reset,
    input up_down,
    output reg [3:0] count
);

always @(posedge clk or posedge reset)
begin
    if (reset)
        count <= 4'b0000;
    else if (up_down)
        count <= count + 1;
    else
        count <= count - 1;
end

endmodule

06_Up_Down_Counter/tb_up_down_counter.v
`timescale 1ps/1ps

module tb_up_down_counter;

reg clk;
reg reset;
reg up_down;
wire [3:0] count;

up_down_counter uut(
    .clk(clk),
    .reset(reset),
    .up_down(up_down),
    .count(count)
);

// Clock Generation
always #5000 clk = ~clk;

initial
begin
    clk = 0;
    reset = 1;
    up_down = 1;

    #10000;
    reset = 0;

    // Count Up
    #50000;

    // Change Direction
    up_down = 0;

    // Count Down
    #50000;

    $finish;
end

initial
begin
    $dumpfile("up_down_counter.vcd");
    $dumpvars(0, tb_up_down_counter);

    $display("Time\tReset\tUpDown\tCount");

    $monitor("%0t\t%b\t%b\t%b",
             $time,
             reset,
             up_down,
             count);
end

endmodule

06_Up_Down_Counter/up_down_counter.vcd
$date
	Fri Jul 10 15:45:30 2026
$end
$version
	Icarus Verilog
$end
$timescale
	1ps
$end
$scope module tb_up_down_counter $end
$var wire 4 ! count [3:0] $end
$var reg 1 " clk $end
$var reg 1 # reset $end
$var reg 1 $ up_down $end
$scope module uut $end
$var wire 1 " clk $end
$var wire 1 # reset $end
$var wire 1 $ up_down $end
$var reg 4 % count [3:0] $end
$upscope $end
$upscope $end
$enddefinitions $end
$comment Show the parameter values. $end
$dumpall
$end
#0
$dumpvars
b0 %
1$
1#
0"
b0 !
$end
#5000
1"
#10000
0"
0#
#15000
b1 !
b1 %
1"
#20000
0"
#25000
b10 !
b10 %
1"
#30000
0"
#35000
b11 !
b11 %
1"
#40000
0"
#45000
b100 !
b100 %
1"
#50000
0"
#55000
b101 !
b101 %
1"
#60000
0"
0$
#65000
b100 !
b100 %
1"
#70000
0"
#75000
b11 !
b11 %
1"
#80000
0"
#85000
b10 !
b10 %
1"
#90000
0"
#95000
b1 !
b1 %
1"
#100000
0"
#105000
b0 !
b0 %
1"
