10_traffic_controller/10_traffic_light_controller.v
module traffic_light_controller(
    input clk,
    input reset,
    output reg [2:0] light
);

parameter RED    = 2'b00,
          GREEN  = 2'b01,
          YELLOW = 2'b10;

reg [1:0] state;

always @(posedge clk or posedge reset)
begin
    if (reset)
        state <= RED;
    else
    begin
        case(state)
            RED:    state <= GREEN;
            GREEN:  state <= YELLOW;
            YELLOW: state <= RED;
            default: state <= RED;
        endcase
    end
end

always @(*)
begin
    case(state)
        RED:    light = 3'b100;
        GREEN:  light = 3'b001;
        YELLOW: light = 3'b010;
        default: light = 3'b100;
    endcase
end

endmodule

10_traffic_controller/tb_10_traffic_light_controller.v
`timescale 1ns/1ps

module tb_traffic_light_controller;

reg clk;
reg reset;
wire [2:0] light;

traffic_light_controller uut (
    .clk(clk),
    .reset(reset),
    .light(light)
);

// Clock Generation
always #5 clk = ~clk;

initial
begin
    $dumpfile("traffic_light.vcd");
    $dumpvars(0, tb_traffic_light_controller);

    clk = 0;
    reset = 1;

    #10 reset = 0;

    #60;

    $finish;
end

initial
begin
    $display("Time\tReset\tLight");
    $monitor("%0t\t%b\t%b", $time, reset, light);
end

endmodule

10_traffic_controller/traffic_light.vcd
$date
	Sat Jul 11 08:19:24 2026
$end
$version
	Icarus Verilog
$end
$timescale
	1ps
$end
$scope module tb_traffic_light_controller $end
$var wire 3 ! light [2:0] $end
$var reg 1 " clk $end
$var reg 1 # reset $end
$scope module uut $end
$var wire 1 " clk $end
$var wire 1 # reset $end
$var parameter 2 $ GREEN $end
$var parameter 2 % RED $end
$var parameter 2 & YELLOW $end
$var reg 3 ' light [2:0] $end
$var reg 2 ( state [1:0] $end
$upscope $end
$upscope $end
$enddefinitions $end
$comment Show the parameter values. $end
$dumpall
b10 &
b0 %
b1 $
$end
#0
$dumpvars
b0 (
b100 '
1#
0"
b100 !
$end
#5000
1"
#10000
0"
0#
#15000
b1 !
b1 '
b1 (
1"
#20000
0"
#25000
b10 !
b10 '
b10 (
1"
#30000
0"
#35000
b100 !
b100 '
b0 (
1"
#40000
0"
#45000
b1 !
b1 '
b1 (
1"
#50000
0"
#55000
b10 !
b10 '
b10 (
1"
#60000
0"
#65000
b100 !
b100 '
b0 (
1"
